LICENSE
MANIFEST.in
README.rst
setup.py
PyMU.egg-info/PKG-INFO
PyMU.egg-info/SOURCES.txt
PyMU.egg-info/dependency_links.txt
PyMU.egg-info/entry_points.txt
PyMU.egg-info/requires.txt
PyMU.egg-info/top_level.txt
pymu/__init__.py
pymu/client.py
pymu/pmuCommandFrame.py
pymu/pmuConfigFrame.py
pymu/pmuDataFrame.py
pymu/pmuEnum.py
pymu/pmuFrame.py
pymu/pmuLib.py
pymu/server.py
pymu/tools.py
pymu/transferFrame.py