Metadata-Version: 1.1
Name: PyMU
Version: 0.2.23
Summary: C37.118 (PMU) data parser
Home-page: https://code.iti.illinois.edu/cdrew3/PyMU
Author: Information Trust Institute
Author-email: cdrew3@illinois.edu
License: MIT
Keywords: development PMU Phasor
Platform: UNKNOWN
Classifier: Development Status :: 3 - Alpha
Classifier: Intended Audience :: Developers
Classifier: Intended Audience :: Science/Research
Classifier: Topic :: Scientific/Engineering :: Interface Engine/Protocol Translator
Classifier: License :: OSI Approved :: MIT License
Classifier: Programming Language :: Python :: 3
Classifier: Programming Language :: Python :: 3.3
Classifier: Programming Language :: Python :: 3.4
Classifier: Programming Language :: Python :: 3.5
Classifier: Environment :: MacOS X
Classifier: Environment :: Win32 (MS Windows)
Classifier: Environment :: Console
